model_monitoring/__init__.py
model_monitoring/additional_metrics.py
model_monitoring/config.py
model_monitoring/imputer.py
model_monitoring/utils.py
model_monitoring/XAI/__init__.py
model_monitoring/XAI/xai.py
model_monitoring/XAI_drift/XAI_drift.py
model_monitoring/XAI_drift/__init__.py
model_monitoring/config/algorithm_settings.yml
model_monitoring/config/params.yml
model_monitoring/data_drift/__init__.py
model_monitoring/data_drift/data_drift.py
model_monitoring/fairness_drift/__init__.py
model_monitoring/fairness_drift/fairness_drift.py
model_monitoring/fairness_measures/__init__.py
model_monitoring/fairness_measures/fairness_measures.py
model_monitoring/model_performance/__init__.py
model_monitoring/model_performance/model_performance.py
model_monitoring/performance_measures/__init__.py
model_monitoring/performance_measures/performance_measures.py
model_monitoring/reference_metadata/__init__.py
model_monitoring/reference_metadata/reference_metadata.py
model_monitoring-2.1.0.dist-info/LICENCE
model_monitoring-2.1.0.dist-info/METADATA
model_monitoring-2.1.0.dist-info/WHEEL
model_monitoring-2.1.0.dist-info/top_level.txt
model_monitoring-2.1.0.dist-info/RECORD
