Metadata-Version: 2.1
Name: model-monitoring
Version: 2.1.0
Summary: Model Monitoring
Home-page: https://dev.azure.com/credem-data/DAT/_git/model_monitoring
Author: DAT Team Credem
Project-URL: Homepage, https://dev.azure.com/credem-data/DAT/_git/model_monitoring
Classifier: Programming Language :: Python :: 3
Classifier: License :: OSI Approved :: MIT License
Classifier: Operating System :: OS Independent
Requires-Python: >=3.12
License-File: LICENCE
Requires-Dist: numpy >=1.26.0
Requires-Dist: pandas >=2.1.0
Requires-Dist: scikit-learn >=1.3.0
Requires-Dist: lightgbm >=4.0.0
Requires-Dist: scipy >=1.11.0
Requires-Dist: PyYAML >=6.0.1
Requires-Dist: shap >=0.44.0
Requires-Dist: ipython
Requires-Dist: numba >=0.59.0
